trytond/modules/health_insurance/COPYING
trytond/modules/health_insurance/README.rst
trytond/modules/health_insurance/__init__.py
trytond/modules/health_insurance/data/messages/messages.xml
trytond/modules/health_insurance/exceptions.py
trytond/modules/health_insurance/health_insurance.py
trytond/modules/health_insurance/health_insurance_view.xml
trytond/modules/health_insurance/locale/ar.po
trytond/modules/health_insurance/locale/de.po
trytond/modules/health_insurance/locale/el.po
trytond/modules/health_insurance/locale/eo.po
trytond/modules/health_insurance/locale/es.po
trytond/modules/health_insurance/locale/fr.po
trytond/modules/health_insurance/locale/health_insurance.pot
trytond/modules/health_insurance/locale/it_IT.po
trytond/modules/health_insurance/locale/ja_JP.po
trytond/modules/health_insurance/locale/ka.po
trytond/modules/health_insurance/locale/lo.po
trytond/modules/health_insurance/locale/pt_BR.po
trytond/modules/health_insurance/locale/sv.po
trytond/modules/health_insurance/locale/tr.po
trytond/modules/health_insurance/locale/uk.po
trytond/modules/health_insurance/locale/zh_CN.po
trytond/modules/health_insurance/pyproject.toml
trytond/modules/health_insurance/tests/__init__.py
trytond/modules/health_insurance/tests/test_health_insurance.py
trytond/modules/health_insurance/tryton.cfg
trytond/modules/health_insurance/view/gnuhealth_health_service.xml
trytond/modules/health_insurance/view/gnuhealth_insurance_plan.xml
trytond/modules/health_insurance/view/gnuhealth_insurance_plan_product_policy.xml
trytond/modules/health_insurance/view/gnuhealth_insurance_plan_product_policy_tree.xml
trytond/modules/health_insurance/view/gnuhealth_patient_procedure_form.xml
trytond/modules/health_insurance/view/gnuhealth_patient_procedure_tree.xml
trytond/modules/health_insurance/wizard/__init__.py
trytond/modules/health_insurance/wizard/wizard_health_insurance.py
gnuhealth_insurance-5.0.2.dist-info/METADATA
gnuhealth_insurance-5.0.2.dist-info/WHEEL
gnuhealth_insurance-5.0.2.dist-info/licenses/COPYING
gnuhealth_insurance-5.0.2.dist-info/RECORD
